CMakeLists.txt
LICENCE
MANIFEST.in
README.md
pyproject.toml
setup.py
TorchImager/__init__.py
TorchImager/main.cu
TorchImager/main.hip
TorchImager.egg-info/PKG-INFO
TorchImager.egg-info/SOURCES.txt
TorchImager.egg-info/dependency_links.txt
TorchImager.egg-info/requires.txt
TorchImager.egg-info/top_level.txt
tests/test.py